k_time_kit/__init__.py
k_time_kit/duration.py
k_time_kit-0.0.2.dist-info/METADATA
k_time_kit-0.0.2.dist-info/WHEEL
k_time_kit-0.0.2.dist-info/licenses/LICENSE
k_time_kit-0.0.2.dist-info/RECORD
