Metadata-Version: 2.1
Name: k_time_kit
Version: 0.0.2
Summary: A library to represents and easily manipulate duration in the format %y %d %h %m %s
Project-URL: Homepage, https://pypi.org/project/k-time-kit/0.0.1/
Project-URL: Issues, https://github.com/KpihX/k_time_kit/issues
Project-URL: Repository, https://github.com/KpihX/k_time_kit.git
Author-email: KpihX <kapoivha@gmail.com>
Maintainer-email: KpihX <kapoivha@gmail.com>
License: MIT License
License-File: LICENSE
Keywords: date,duration,format,time,timekit
Classifier: Development Status :: 4 - Beta
Classifier: Intended Audience :: Developers
Classifier: License :: OSI Approved :: MIT License
Classifier: Operating System :: OS Independent
Classifier: Programming Language :: Python :: 3
Requires-Python: >=3.8
